{
    "page": 1,
    "results": [
      {
        "backdrop_path": "/7dowXHcFccjmxf0YZYxDFkfVq65.jpg",
        "id": 100088,
        "name": "The Last of Us",
        "original_name": "The Last of Us",
        "overview": "Twenty years after modern civilization has been destroyed, Joel, a hardened survivor, is hired to smuggle Ellie, a 14-year-old girl, out of an oppressive quarantine zone. What starts as a small job soon becomes a brutal, heartbreaking journey, as they both must traverse the United States and depend on each other for survival.",
        "poster_path": "/dmo6TYuuJgaYinXBPjrgG9mB5od.jpg",
        "media_type": "tv",
        "adult": false,
        "original_language": "en",
        "genre_ids": [
          18
        ],
        "popularity": 511.5252,
        "first_air_date": "2023-01-15",
        "vote_average": 8.579,
        "vote_count": 5658,
        "origin_country": [
          "US"
        ],
        "videoUrl": "http://commondatastorage.googleapis.com/gtv-videos-bucket/sample/BigBuckBunny.mp4",
        "release_date": "2025-03-20"
      },
      {
        "backdrop_path": "/dg3OindVAGZBjlT3xYKqIAdukPL.jpg",
        "id": 42009,
        "name": "Black Mirror",
        "original_name": "Black Mirror",
        "overview": "Twisted tales run wild in this mind-bending anthology series that reveals humanity's worst traits, greatest innovations and more.",
        "poster_path": "/seN6rRfN0I6n8iDXjlSMk1QjNcq.jpg",
        "media_type": "tv",
        "adult": false,
        "original_language": "en",
        "genre_ids": [
          10765,
          18,
          9648
        ],
        "popularity": 179.4319,
        "first_air_date": "2011-12-04",
        "vote_average": 8.291,
        "vote_count": 5421,
        "origin_country": [
          "GB"
        ],
        "videoUrl": "http://commondatastorage.googleapis.com/gtv-videos-bucket/sample/ElephantsDream.mp4"
      },
      {
        "backdrop_path": "/vIioWssbxRtEkIzgj8r0pCWYkYM.jpg",
        "id": 157744,
        "name": "1923",
        "original_name": "1923",
        "overview": "Follow a new generation of the Dutton family during the early twentieth century when pandemics, historic drought, the end of Prohibition and the Great Depression all plague the mountain west, and the Duttons who call it home.",
        "poster_path": "/vNJWr0xh7W5IDzFTnVzWhw6KoJr.jpg",
        "media_type": "tv",
        "adult": false,
        "original_language": "en",
        "genre_ids": [
          18,
          37
        ],
        "popularity": 60.2785,
        "first_air_date": "2022-12-18",
        "vote_average": 8.2,
        "vote_count": 536,
        "origin_country": [
          "US"
        ],
        "videoUrl": "http://commondatastorage.googleapis.com/gtv-videos-bucket/sample/BigBuckBunny.mp4",
        "release_date": "2025-03-20"
      },
      {
        "backdrop_path": "/w8NsengOrWLapYBVutr52gwWMio.jpg",
        "id": 275388,
        "name": "The Glass Dome",
        "original_name": "Glaskupan",
        "overview": "When her friend's daughter goes missing, criminologist Lejla joins the search — and must confront the haunting trauma of her own childhood abduction.",
        "poster_path": "/yn4PIMnXJ42lObinYtmIvQ9lVtm.jpg",
        "media_type": "tv",
        "adult": false,
        "original_language": "sv",
        "genre_ids": [
          18,
          80
        ],
        "popularity": 110.0077,
        "first_air_date": "2025-04-15",
        "vote_average": 7.184,
        "vote_count": 38,
        "origin_country": [
          "SE"
        ],
        "videoUrl": "http://commondatastorage.googleapis.com/gtv-videos-bucket/sample/TearsOfSteel.mp4",
        "release_date": "2025-03-20"
      },
      {
        "backdrop_path": "/gzOIymABxmetAECXtazEYCpMmfb.jpg",
        "id": 78191,
        "name": "You",
        "original_name": "You",
        "overview": "A dangerously charming, intensely obsessive young man goes to extreme measures to insert himself into the lives of those he is transfixed by.",
        "poster_path": "/vzgsobZmNxJyJ64ejTOUXvJ9UBn.jpg",
        "media_type": "tv",
        "adult": false,
        "original_language": "en",
        "genre_ids": [
          18
        ],
        "popularity": 61.7163,
        "first_air_date": "2018-09-09",
        "vote_average": 8.043,
        "vote_count": 3339,
        "origin_country": [
          "US"
        ],
        "videoUrl": "http://commondatastorage.googleapis.com/gtv-videos-bucket/sample/TearsOfSteel.mp4",
        "release_date": "2025-03-20"
      },
      {
        "backdrop_path": "/tMG8CERbBIGmDAGm5IetMy5m8hF.jpg",
        "id": 204284,
        "name": "The Rehearsal",
        "original_name": "The Rehearsal",
        "overview": "With a construction crew, a legion of actors, and seemingly unlimited resources, Nathan Fielder allows ordinary people to prepare for life’s biggest moments by “rehearsing” them in carefully crafted simulations of his own design. When a single misstep could shatter your entire world, why leave life to chance?",
        "poster_path": "/mIevNYxovnH4sR22qkUmAgS5vdv.jpg",
        "media_type": "tv",
        "adult": false,
        "original_language": "en",
        "genre_ids": [
          35,
          99
        ],
        "popularity": 26.5789,
        "first_air_date": "2022-07-15",
        "vote_average": 8,
        "vote_count": 180,
        "origin_country": [
          "US"
        ],
        "videoUrl": "http://commondatastorage.googleapis.com/gtv-videos-bucket/sample/BigBuckBunny.mp4",
        "release_date": "2025-03-20"
      },
      {
        "backdrop_path": "/29P64FqDp0UVa9oJsIl49PHn5tH.jpg",
        "id": 240993,
        "name": "Ransom Canyon",
        "original_name": "Ransom Canyon",
        "overview": "Passions run deep in a small Texas town, as three ranching dynasties fight for their land, their legacies and the people they love.",
        "poster_path": "/vp6A0mthGwZmnowmLxqNPF0lVRN.jpg",
        "media_type": "tv",
        "adult": false,
        "original_language": "en",
        "genre_ids": [
          18,
          37
        ],
        "popularity": 33.0047,
        "first_air_date": "2025-04-17",
        "vote_average": 7.325,
        "vote_count": 20,
        "origin_country": [
          "US"
        ],
        "videoUrl": "http://commondatastorage.googleapis.com/gtv-videos-bucket/sample/BigBuckBunny.mp4",
        "release_date": "2025-03-20"
      },
      {
        "backdrop_path": "/jXB3OoWPkojsOP2O2OoLCeAIDRS.jpg",
        "id": 69478,
        "name": "The Handmaid's Tale",
        "original_name": "The Handmaid's Tale",
        "overview": "Set in a dystopian future, a woman is forced to live as a concubine under a fundamentalist theocratic dictatorship. A TV adaptation of Margaret Atwood's novel.",
        "poster_path": "/qdWEaWkIQIjANGFeskheXpP0mm1.jpg",
        "media_type": "tv",
        "adult": false,
        "original_language": "en",
        "genre_ids": [
          18,
          10765
        ],
        "popularity": 112.8689,
        "first_air_date": "2017-04-26",
        "vote_average": 8.2,
        "vote_count": 2855,
        "origin_country": [
          "US"
        ],
        "videoUrl": "http://commondatastorage.googleapis.com/gtv-videos-bucket/sample/BigBuckBunny.mp4",
        "release_date": "2025-03-20"
      },
      {
        "backdrop_path": "/ixgFmf1X59PUZam2qbAfskx2gQr.jpg",
        "id": 95396,
        "name": "Severance",
        "original_name": "Severance",
        "overview": "Mark leads a team of office workers whose memories have been surgically divided between their work and personal lives. When a mysterious colleague appears outside of work, it begins a journey to discover the truth about their jobs.",
        "poster_path": "/pPHpeI2X1qEd1CS1SeyrdhZ4qnT.jpg",
        "media_type": "tv",
        "adult": false,
        "original_language": "en",
        "genre_ids": [
          18,
          9648,
          10765
        ],
        "popularity": 65.554,
        "first_air_date": "2022-02-17",
        "vote_average": 8.4,
        "vote_count": 1905,
        "origin_country": [
          "US"
        ],
        "videoUrl": "http://commondatastorage.googleapis.com/gtv-videos-bucket/sample/BigBuckBunny.mp4",
        "release_date": "2025-03-20"
      },
      {
        "backdrop_path": "/odVlTMqPPiMksmxpN9cCbPCjUPP.jpg",
        "id": 127532,
        "name": "Solo Leveling",
        "original_name": "俺だけレベルアップな件",
        "overview": "They say whatever doesn’t kill you makes you stronger, but that’s not the case for the world’s weakest hunter Sung Jinwoo. After being brutally slaughtered by monsters in a high-ranking dungeon, Jinwoo came back with the System, a program only he could see, that’s leveling him up in every way. Now, he’s inspired to discover the secrets behind his powers and the dungeon that spawned them.",
        "poster_path": "/geCRueV3ElhRTr0xtJuEWJt6dJ1.jpg",
        "media_type": "tv",
        "adult": false,
        "original_language": "ja",
        "genre_ids": [
          16,
          10759,
          10765
        ],
        "popularity": 159.3509,
        "first_air_date": "2024-01-07",
        "vote_average": 8.638,
        "vote_count": 1091,
        "origin_country": [
          "JP"
        ],
        "videoUrl": "http://commondatastorage.googleapis.com/gtv-videos-bucket/sample/BigBuckBunny.mp4",
        "release_date": "2025-03-20"
      },
      {
        "backdrop_path": "/gDtZQmfzvErZpeXOVeCBQE9WkSF.jpg",
        "id": 239770,
        "name": "Doctor Who",
        "original_name": "Doctor Who",
        "overview": "The Doctor and his companion travel across time and space encountering incredible friends and foes.",
        "poster_path": "/2JP6NSmBwxg75uTcIHiv5R8PpPi.jpg",
        "media_type": "tv",
        "adult": false,
        "original_language": "en",
        "genre_ids": [
          10759,
          18,
          10765
        ],
        "popularity": 30.1025,
        "first_air_date": "2024-05-11",
        "vote_average": 6.505,
        "vote_count": 196,
        "origin_country": [
          "GB"
        ],
        "videoUrl": "http://commondatastorage.googleapis.com/gtv-videos-bucket/sample/BigBuckBunny.mp4",
        "release_date": "2025-03-20"
      },
      {
        "backdrop_path": "/i9r8zKZDMNyWV3ebjP7zvYLpx5b.jpg",
        "id": 247718,
        "name": "MobLand",
        "original_name": "MobLand",
        "overview": "Two mob families clash in a war that threatens to topple empires and lives.",
        "poster_path": "/abeH7n5pcuQcwYcTxG6DTZvXLP1.jpg",
        "media_type": "tv",
        "adult": false,
        "original_language": "en",
        "genre_ids": [
          80,
          18
        ],
        "popularity": 38.4743,
        "first_air_date": "2025-03-30",
        "vote_average": 8.5,
        "vote_count": 56,
        "origin_country": [
          "GB",
          "US"
        ],
        "videoUrl": "http://commondatastorage.googleapis.com/gtv-videos-bucket/sample/BigBuckBunny.mp4",
        "release_date": "2025-03-20"
      },
      {
        "backdrop_path": "/2rmK7mnchw9Xr3XdiTFSxTTLXqv.jpg",
        "id": 37854,
        "name": "One Piece",
        "original_name": "ワンピース",
        "overview": "Years ago, the fearsome Pirate King, Gol D. Roger was executed leaving a huge pile of treasure and the famous \"One Piece\" behind. Whoever claims the \"One Piece\" will be named the new King of the Pirates.\n\nMonkey D. Luffy, a boy who consumed a \"Devil Fruit,\" decides to follow in the footsteps of his idol, the pirate Shanks, and find the One Piece. It helps, of course, that his body has the properties of rubber and that he's surrounded by a bevy of skilled fighters and thieves to help him along the way.\n\nLuffy will do anything to get the One Piece and become King of the Pirates!",
        "poster_path": "/cMD9Ygz11zjJzAovURpO75Qg7rT.jpg",
        "media_type": "tv",
        "adult": false,
        "original_language": "ja",
        "genre_ids": [
          10759,
          35,
          16
        ],
        "popularity": 54.6638,
        "first_air_date": "1999-10-20",
        "vote_average": 8.7,
        "vote_count": 4856,
        "origin_country": [
          "JP"
        ],
        "videoUrl": "http://commondatastorage.googleapis.com/gtv-videos-bucket/sample/BigBuckBunny.mp4",
        "release_date": "2025-03-20"
      },
      {
        "backdrop_path": "/pxeqQX4qFQ0cVxPt5SWZENV5BH3.jpg",
        "id": 456,
        "name": "The Simpsons",
        "original_name": "The Simpsons",
        "overview": "Set in Springfield, the average American town, the show focuses on the antics and everyday adventures of the Simpson family; Homer, Marge, Bart, Lisa and Maggie, as well as a virtual cast of thousands. Since the beginning, the series has been a pop culture icon, attracting hundreds of celebrities to guest star. The show has also made name for itself in its fearless satirical take on politics, media and American life in general.",
        "poster_path": "/vHqeLzYl3dEAutojCO26g0LIkom.jpg",
        "media_type": "tv",
        "adult": false,
        "original_language": "en",
        "genre_ids": [
          10751,
          16,
          35
        ],
        "popularity": 187.4693,
        "first_air_date": "1989-12-17",
        "vote_average": 8.016,
        "vote_count": 10160,
        "origin_country": [
          "US"
        ],
        "videoUrl": "http://commondatastorage.googleapis.com/gtv-videos-bucket/sample/BigBuckBunny.mp4",
        "release_date": "2025-03-20"
      },
      {
        "backdrop_path": "/dDx7bjxtJcMwUhowCn7VhPwLEzp.jpg",
        "id": 233256,
        "name": "The Stolen Girl",
        "original_name": "The Stolen Girl",
        "overview": "A mother-of-two has her world turned upside down when she agrees to let her nine-year-old daughter have a sleepover at her new best friend's house.",
        "poster_path": "/dukqZNsr9vlzfAEa8xAABRT3yxD.jpg",
        "media_type": "tv",
        "adult": false,
        "original_language": "en",
        "genre_ids": [
          18,
          9648
        ],
        "popularity": 22.5874,
        "first_air_date": "2025-04-16",
        "vote_average": 6.3,
        "vote_count": 19,
        "origin_country": [
          "GB"
        ],
        "videoUrl": "http://commondatastorage.googleapis.com/gtv-videos-bucket/sample/BigBuckBunny.mp4",
        "release_date": "2025-03-20"
      },
      {
        "backdrop_path": "/zZqpAXxVSBtxV9qPBcscfXBcL2w.jpg",
        "id": 1399,
        "name": "Game of Thrones",
        "original_name": "Game of Thrones",
        "overview": "Seven noble families fight for control of the mythical land of Westeros. Friction between the houses leads to full-scale war. All while a very ancient evil awakens in the farthest north. Amidst the war, a neglected military order of misfits, the Night's Watch, is all that stands between the realms of men and icy horrors beyond.",
        "poster_path": "/1XS1oqL89opfnbLl8WnZY1O1uJx.jpg",
        "media_type": "tv",
        "adult": false,
        "original_language": "en",
        "genre_ids": [
          10765,
          18,
          10759
        ],
        "popularity": 186.3141,
        "first_air_date": "2011-04-17",
        "vote_average": 8.456,
        "vote_count": 24887,
        "origin_country": [
          "US"
        ],
        "videoUrl": "http://commondatastorage.googleapis.com/gtv-videos-bucket/sample/BigBuckBunny.mp4",
        "release_date": "2025-03-20"
      },
      {
        "backdrop_path": "/hrsRczdsAHBLTDzlIqt82bxY0Tt.jpg",
        "id": 202555,
        "name": "Daredevil: Born Again",
        "original_name": "Daredevil: Born Again",
        "overview": "Matt Murdock, a blind lawyer with heightened abilities, is fighting for justice through his bustling law firm, while former mob boss Wilson Fisk pursues his own political endeavors in New York. When their past identities begin to emerge, both men find themselves on an inevitable collision course.",
        "poster_path": "/9lLuhV703HGCbnz6FxnqCwIwzAZ.jpg",
        "media_type": "tv",
        "adult": false,
        "original_language": "en",
        "genre_ids": [
          18,
          80
        ],
        "popularity": 131.361,
        "first_air_date": "2025-03-04",
        "vote_average": 8.165,
        "vote_count": 346,
        "origin_country": [
          "US"
        ],
        "videoUrl": "http://commondatastorage.googleapis.com/gtv-videos-bucket/sample/BigBuckBunny.mp4",
        "release_date": "2025-03-20"
      },
      {
        "backdrop_path": "/1P3QtW1IkivqDrKbbwuR0zCYIf8.jpg",
        "id": 71914,
        "name": "The Wheel of Time",
        "original_name": "The Wheel of Time",
        "overview": "Follow Moiraine, a member of the shadowy and influential all-female organization called the “Aes Sedai” as she embarks on a dangerous, world-spanning journey with five young men and women. Moiraine believes one of them might be the reincarnation of an incredibly powerful individual, whom prophecies say will either save humanity or destroy it.",
        "poster_path": "/eVm7vI0VTUKYzgpOXCUu9qz3L4E.jpg",
        "media_type": "tv",
        "adult": false,
        "original_language": "en",
        "genre_ids": [
          10765,
          18
        ],
        "popularity": 124.7884,
        "first_air_date": "2021-11-18",
        "vote_average": 7.673,
        "vote_count": 2202,
        "origin_country": [
          "US"
        ],
        "videoUrl": "http://commondatastorage.googleapis.com/gtv-videos-bucket/sample/BigBuckBunny.mp4",
        "release_date": "2025-03-20"
      },
      {
        "backdrop_path": "/iHSwvRVsRyxpX7FE7GbviaDvgGZ.jpg",
        "id": 119051,
        "name": "Wednesday",
        "original_name": "Wednesday",
        "overview": "Wednesday Addams is sent to Nevermore Academy, a bizarre boarding school where she attempts to master her psychic powers, stop a monstrous killing spree of the town citizens, and solve the supernatural mystery that affected her family 25 years ago — all while navigating her new relationships.",
        "poster_path": "/9PFonBhy4cQy7Jz20NpMygczOkv.jpg",
        "media_type": "tv",
        "adult": false,
        "original_language": "en",
        "genre_ids": [
          10765,
          9648,
          35
        ],
        "popularity": 29.5821,
        "first_air_date": "2022-11-23",
        "vote_average": 8.4,
        "vote_count": 8988,
        "origin_country": [
          "US"
        ],
        "videoUrl": "http://commondatastorage.googleapis.com/gtv-videos-bucket/sample/BigBuckBunny.mp4",
        "release_date": "2025-03-20"
      },
      {
        "backdrop_path": "/vcFW09U4834DyFOeRZpsx9x1D3S.jpg",
        "id": 57243,
        "name": "Doctor Who",
        "original_name": "Doctor Who",
        "overview": "The Doctor is a Time Lord: a 900 year old alien with 2 hearts, part of a gifted civilization who mastered time travel. The Doctor saves planets for a living—more of a hobby actually, and the Doctor's very, very good at it.",
        "poster_path": "/4edFyasCrkH4MKs6H4mHqlrxA6b.jpg",
        "media_type": "tv",
        "adult": false,
        "original_language": "en",
        "genre_ids": [
          10759,
          18,
          10765
        ],
        "popularity": 167.706,
        "first_air_date": "2005-03-26",
        "vote_average": 7.541,
        "vote_count": 3100,
        "origin_country": [
          "GB"
        ],
        "videoUrl": "http://commondatastorage.googleapis.com/gtv-videos-bucket/sample/BigBuckBunny.mp4",
        "release_date": "2025-03-20"
      }
    ],
    "total_pages": 500,
    "total_results": 10000
  }